{
  "White-throated Fantail_274.jpeg": "https://i.ytimg.com/vi/6i6S4cINSCA/maxresdefault.jpg",
  "Yellow-billed Loon_26.jpeg": "https://i.ytimg.com/vi/yA0LyzgaPnI/maxresdefault.jpg",
  "White-bellied Woodpecker_163.jpeg": "https://i.ytimg.com/vi/T5BloGJ8Gbw/hqdefault.jpg",
  "Hwamei_39.jpeg": "https://i.ytimg.com/vi/RdwKd3ao_Nc/hqdefault.jpg",
  "Hill Myna_240.jpeg": "https://i.ytimg.com/vi/6i6S4cINSCA/hqdefault.jpg",
  "White-Rumped Sandpiper_78.jpeg": "https://i.ytimg.com/vi/vkieVESI_MA/hqdefault.jpg",
  "Yellow-footed Green-Pigeo_279.jpeg": "https://i.ytimg.com/vi/qL3FMIMtrbk/hqdefault.jpg",
  "Spot-winged Grosbeak_400.jpeg": "https://i.ytimg.com/vi/atYSR1MtU6A/hqdefault.jpg",
  "Yellowish-bellied Bush Warbler_206.jpeg": "https://i.ytimg.com/vi/HgulTl5__EA/maxresdefault.jpg",
  "White-breasted Waterhen_117.jpeg": "https://i.ytimg.com/vi/DLPslYHPdEQ/hqdefault.jpg",
  "Ultramarine Flycatcher_91.jpeg": "https://i.ytimg.com/vi/L6V1VnGAzBE/maxresdefault.jpg",
  "Yellow Wagtail_277.jpeg": "https://i.ytimg.com/vi/0_05djjHx_Q/maxresdefault.jpg",
  "Pleske's Warbler_250.jpeg": "https://static.inaturalist.org/photos/667695/original.jpg?1545539124",
  "Small Pratincole_8.jpeg": "https://i.ytimg.com/vi/yWZ37RigsRs/maxresdefault.jpg",
  "White Eared-Pheasant_52.jpeg": "https://i.ytimg.com/vi/dTXOFqxKsKk/maxresdefault.jpg",
  "Upland Pipit_197.jpeg": "https://i.ytimg.com/vi/Q-X-TDE2fG8/hqdefault.jpg"
}