{"Wigeon_81.jpeg": {"image_description": "Blue-throated Bee Eater Bird from Stock Footage Video (100% Royalty ...", "image_filename": "Wigeon_81.jpeg", "image_format": "jpg", "image_height": 480, "image_host": "shutterstock.com", "image_link": "https://ak5.picdn.net/shutterstock/videos/1934485/thumb/1.jpg", "image_source": "https://www.shutterstock.com/video/clip-1934485-blue-throated-bee-eater-bird-thailand", "image_thumbnail_url": "https://encrypted-tbn0.gstatic.com/images?q=tbn:ANd9GcT2x8qGHDJyfqMkCOag7ftCwKQtkncF6SKk60Rgdc_HX2HLB05I", "image_width": 852}, "Yellow-breasted Bunting_108.jpeg": {"image_description": "Bird - Blue-throated Bee-eater hunting butterfly at Singapore Pasir ...", "image_filename": "Yellow-breasted Bunting_108.jpeg", "image_format": "jpg", "image_height": 720, "image_host": "youtube.com", "image_link": "https://i.ytimg.com/vi/nP1XK3UjxVQ/maxresdefault.jpg", "image_source": "https://www.youtube.com/watch?v=nP1XK3UjxVQ", "image_thumbnail_url": "https://encrypted-tbn0.gstatic.com/images?q=tbn:ANd9GcQCyxKuWXBBLvLKFayoiIlDVJEUApi4Vt0EACANK057yeXA3YgrWg", "image_width": 1280}, "White-tailed Rubythroat_16.jpeg": {"image_description": "Blue throated Bee eater (Merops viridis) - YouTube", "image_filename": "White-tailed Rubythroat_16.jpeg", "image_format": "jpg", "image_height": 720, "image_host": "youtube.com", "image_link": "https://i.ytimg.com/vi/rdCI9XxM-Ag/maxresdefault.jpg", "image_source": "https://www.youtube.com/watch?v=rdCI9XxM-Ag", "image_thumbnail_url": "https://encrypted-tbn0.gstatic.com/images?q=tbn:ANd9GcSClV6Qia-8Dc7UKPg5WDWJZv5PemMTUZQyyMk-iDkLNaHhdm-hGg", "image_width": 1280}, "White-whiskered Laughingthrush_291.jpeg": {"image_description": "Blue Throated Bee Eater HD - YouTube", "image_filename": "White-whiskered Laughingthrush_291.jpeg", "image_format": "jpg", "image_height": 720, "image_host": "youtube.com", "image_link": "https://i.ytimg.com/vi/51Tpif4dguE/maxresdefault.jpg", "image_source": "https://www.youtube.com/watch?v=51Tpif4dguE", "image_thumbnail_url": "https://encrypted-tbn0.gstatic.com/images?q=tbn:ANd9GcT9d8nztg0H5ufZ8DozoGMT4AjjCl2xC7tmm_11HD2Ntvv30jd5", "image_width": 1280}, "White-browed Fantail_357.jpeg": {"image_description": "Blue-throated Bee-eater - YouTube", "image_filename": "White-browed Fantail_357.jpeg", "image_format": "jpg", "image_height": 720, "image_host": "youtube.com", "image_link": "https://i.ytimg.com/vi/3MKIuCRdxhI/maxresdefault.jpg", "image_source": "https://www.youtube.com/watch?v=3MKIuCRdxhI", "image_thumbnail_url": "https://encrypted-tbn0.gstatic.com/images?q=tbn:ANd9GcQnurhW7jHf7bBUj7qoQ9wXFCXzyH7ktmh4Mb3M_NJZOD4YLjNn", "image_width": 1280}, "Streaked Reed-Warbler_66.jpeg": {"image_description": "Blue-throated Bee-Eater (Merops viridis) \u00c2\u00b7 iNaturalist.org", "image_filename": "Streaked Reed-Warbler_66.jpeg", "image_format": "jpg", "image_height": 800, "image_host": "inaturalist.org", "image_link": "https://static.inaturalist.org/photos/12220254/original.jpg?1512485091", "image_source": "https://www.inaturalist.org/taxa/204541-Merops-viridis", "image_thumbnail_url": "https://encrypted-tbn0.gstatic.com/images?q=tbn:ANd9GcQxu-U7hbnY_4b_BX4MnyvZ254yS8QulBZACvUgdQSm8J6q6uBu", "image_width": 534}, "White-browed Chinese Warb_49.jpeg": {"image_description": "Blue Throated Bee Eater - YouTube", "image_filename": "White-browed Chinese Warb_49.jpeg", "image_format": "jpg", "image_height": 720, "image_host": "youtube.com", "image_link": "https://i.ytimg.com/vi/Kc5v2SIiJGA/maxresdefault.jpg", "image_source": "https://www.youtube.com/watch?v=Kc5v2SIiJGA", "image_thumbnail_url": "https://encrypted-tbn0.gstatic.com/images?q=tbn:ANd9GcQckFyRM0lfsw75DNqPROPA4a3JifbwzZ2htb8JFwbEqkiNUujI_Q", "image_width": 1280}, "Rufous-capped Babbler_323.jpeg": {"image_description": "A LATE 20TH CENTURY TAXIDERMY BLUE-THROATED BEE-EATER Mounted on a ...", "image_filename": "Rufous-capped Babbler_323.jpeg", "image_format": "jpg", "image_height": 1400, "image_host": "the-saleroom.com", "image_link": "https://cdn.globalauctionplatform.com/91fcd4e9-8a6b-49b5-b088-a82400e5e64d/87c4cb7e-9862-406b-aa08-314f123e48e1/original.jpg", "image_source": "https://www.the-saleroom.com/en-gb/auction-catalogues/the-swan-at-tetsworth/catalogue-id-srsw10059/lot-49c81ba7-628d-4316-ba59-a838012fb0ae", "image_thumbnail_url": "https://encrypted-tbn0.gstatic.com/images?q=tbn:ANd9GcRub46rZvHffIp9UocvCLxlZ8cBcZeqlD766wa2hbBXsbXPM6oA", "image_width": 1000}, "White-gorgeted Flycatcher_175.jpeg": {"image_description": "AVoCet : Recording of Blue-throated Bee-eater, Merops viridis", "image_filename": "White-gorgeted Flycatcher_175.jpeg", "image_format": "jpg", "image_height": 1008, "image_host": "avocet.integrativebiology.natsci.msu.edu", "image_link": "https://avocet.integrativebiology.natsci.msu.edu/photos_data/886/original.jpg", "image_source": "https://avocet.integrativebiology.natsci.msu.edu/recordings/10151", "image_thumbnail_url": "https://encrypted-tbn0.gstatic.com/images?q=tbn:ANd9GcRhMSUmnVWCF_DcSXab0ungpYRHIeXj7KMpDHH68S0Wdp7oOE3ONw", "image_width": 1038}, "Von Schrenck's Bittern_178.jpeg": {"image_description": "Blue-throated Bee-eater calling - YouTube", "image_filename": "Von Schrenck's Bittern_178.jpeg", "image_format": "jpg", "image_height": 720, "image_host": "youtube.com", "image_link": "https://i.ytimg.com/vi/L5pQ9G8Fw7A/maxresdefault.jpg", "image_source": "https://www.youtube.com/watch?v=L5pQ9G8Fw7A", "image_thumbnail_url": "https://encrypted-tbn0.gstatic.com/images?q=tbn:ANd9GcR129iKGP9RVtB9UH70IPhrQkVi3EwsKQKv9U2IZ5fm38nj6CKOGQ", "image_width": 1280}, "Yellow Wagtail_277.jpeg": {"image_description": "Blue throated Bee-eater - YouTube", "image_filename": "Yellow Wagtail_277.jpeg", "image_format": "jpg", "image_height": 720, "image_host": "youtube.com", "image_link": "https://i.ytimg.com/vi/rLVox5eN69g/maxresdefault.jpg", "image_source": "https://www.youtube.com/watch?v=rLVox5eN69g", "image_thumbnail_url": "https://encrypted-tbn0.gstatic.com/images?q=tbn:ANd9GcThn-9qIVw4jmY_gqZradQU2P3kuEZoVf47R10Ec6yx5xsnCi1b2g", "image_width": 1280}, "Streaked Weaver_92.jpeg": {"image_description": "Blue-throated bee-eater \u00e8\u0093\u009d\u00e5\u0096\u0089\u00e8\u009c\u0082\u00e8\u0099\u008e - YouTube", "image_filename": "Streaked Weaver_92.jpeg", "image_format": "jpg", "image_height": 720, "image_host": "youtube.com", "image_link": "https://i.ytimg.com/vi/mmx8CZDxPjM/maxresdefault.jpg", "image_source": "https://www.youtube.com/watch?v=mmx8CZDxPjM", "image_thumbnail_url": "https://encrypted-tbn0.gstatic.com/images?q=tbn:ANd9GcSn7D6zpF6OhpE-LdK5Djiu96hIIjTvgeCu-3k8L5LH_jdGcFBQ", "image_width": 1280}, "Zitting Cisticola_82.jpeg": {"image_description": "Blue-throated bee eater (Merops viridis) from Sarawak - YouTube", "image_filename": "Zitting Cisticola_82.jpeg", "image_format": "jpg", "image_height": 720, "image_host": "youtube.com", "image_link": "https://i.ytimg.com/vi/DcIxUV_XO6Y/maxresdefault.jpg", "image_source": "https://www.youtube.com/watch?v=DcIxUV_XO6Y", "image_thumbnail_url": "https://encrypted-tbn0.gstatic.com/images?q=tbn:ANd9GcRYwfBjKaR1Hiw1jx8yS9_wmUcQ6YJCREcfzRMoLLyuoWT5sekGaQ", "image_width": 1280}, "White Stork_178.jpeg": {"image_description": "Blue-throated Bee-eater - YouTube", "image_filename": "White Stork_178.jpeg", "image_format": "jpg", "image_height": 720, "image_host": "youtube.com", "image_link": "https://i.ytimg.com/vi/TFKHO4Ztfcw/maxresdefault.jpg", "image_source": "https://www.youtube.com/watch?v=TFKHO4Ztfcw", "image_thumbnail_url": "https://encrypted-tbn0.gstatic.com/images?q=tbn:ANd9GcSxhCmMognECsGWx4886uNaKvUNMbYAlvhuZqxozTmCjfE_A1se", "image_width": 1280}, "Striated Bulbul_48.jpeg": {"image_description": "Blue throated bee eater - YouTube", "image_filename": "Striated Bulbul_48.jpeg", "image_format": "jpg", "image_height": 720, "image_host": "youtube.com", "image_link": "https://i.ytimg.com/vi/R7j_GrN3Jzs/maxresdefault.jpg", "image_source": "https://www.youtube.com/watch?v=R7j_GrN3Jzs", "image_thumbnail_url": "https://encrypted-tbn0.gstatic.com/images?q=tbn:ANd9GcTtRp97XfVjjGMA94txip7yl5yIMEbr867jF3Pdj-YjH6FIpa5J", "image_width": 1280}, "White-cheeked Starling_33.jpeg": {"image_description": "Blue-throated Bee-eater (Merops viridis) throwing up a pellet - YouTube", "image_filename": "White-cheeked Starling_33.jpeg", "image_format": "jpg", "image_height": 720, "image_host": "youtube.com", "image_link": "https://i.ytimg.com/vi/4S-Dyx0l7Hs/maxresdefault.jpg", "image_source": "https://www.youtube.com/watch?v=4S-Dyx0l7Hs", "image_thumbnail_url": "https://encrypted-tbn0.gstatic.com/images?q=tbn:ANd9GcQVNclA1EYFHy34WWbl9ixGVC2wpTFin_36fsU2kiJ71KCr_2VT", "image_width": 1280}, "Tibetan Rosefinch_356.jpeg": {"image_description": "Bird - Blue-throated Bee-eater pair at Singapore Pasir Ris park ...", "image_filename": "Tibetan Rosefinch_356.jpeg", "image_format": "jpg", "image_height": 720, "image_host": "youtube.com", "image_link": "https://i.ytimg.com/vi/Kezs_l8q69s/maxresdefault.jpg", "image_source": "https://www.youtube.com/watch?v=Kezs_l8q69s", "image_thumbnail_url": "https://encrypted-tbn0.gstatic.com/images?q=tbn:ANd9GcRIHtP23pmBgZ9bnSS-oYf-B86oCkPQmkOIk-RolcfPVRKB3AUj", "image_width": 1280}, "White-bellied Green-Pigeo_21.jpeg": {"image_description": "Blue-throated Bee-eater and Blue-tailed Bee-eater in Malaysia - YouTube", "image_filename": "White-bellied Green-Pigeo_21.jpeg", "image_format": "jpg", "image_height": 720, "image_host": "youtube.com", "image_link": "https://i.ytimg.com/vi/tTrRrBcdgx4/maxresdefault.jpg", "image_source": "https://www.youtube.com/watch?v=tTrRrBcdgx4", "image_thumbnail_url": "https://encrypted-tbn0.gstatic.com/images?q=tbn:ANd9GcQbXtO4V90D7koltxhbRGwXPeK95-Z5hALwf383N_bqAkSzfoZPUQ", "image_width": 1280}, "Small Buttonquail_44.jpeg": {"image_description": "Blue Throated Bee Eater & Two Juveniles Feeding - YouTube", "image_filename": "Small Buttonquail_44.jpeg", "image_format": "jpg", "image_height": 720, "image_host": "youtube.com", "image_link": "https://i.ytimg.com/vi/IxnbB8eX3E8/maxresdefault.jpg", "image_source": "https://www.youtube.com/watch?v=IxnbB8eX3E8", "image_thumbnail_url": "https://encrypted-tbn0.gstatic.com/images?q=tbn:ANd9GcTp7mqdk5-Bnv0MZ0Q_ruqyVJh35lWFNPh5QmDKPFSNj1NFtMGcug", "image_width": 1280}}