{"Spotted Wren Babbler_276.jpeg": {"image_description": "Northern Hawk Owls Photo Gallery by Peter Stahl at pbase.com", "image_filename": "Spotted Wren Babbler_276.jpeg", "image_format": "jpg", "image_height": 639, "image_host": "pbase.com", "image_link": "https://pbase.com/decor/image/91584675/original.jpg", "image_source": "https://www.pbase.com/decor/northern_hawk_owls", "image_thumbnail_url": "https://encrypted-tbn0.gstatic.com/images?q=tbn:ANd9GcQX9u_gNO-jVfEu-rbomowF_ByRuJIE8uFH9ZgmjlIpyYFY_sTu", "image_width": 1200}, "Yellow-throated Laughingthrush_397.jpeg": {"image_description": "H\u00c3\u0096KUGGLA Northern Hawk Owl (Surnia ulula) Klipp - 2185 - YouTube", "image_filename": "Yellow-throated Laughingthrush_397.jpeg", "image_format": "jpg", "image_height": 720, "image_host": "youtube.com", "image_link": "https://i.ytimg.com/vi/2YgPiIAXwDM/maxresdefault.jpg", "image_source": "https://www.youtube.com/watch?v=2YgPiIAXwDM", "image_thumbnail_url": "https://encrypted-tbn0.gstatic.com/images?q=tbn:ANd9GcTIX_cz543FcHPf0_HtRLBjTV_vX4rfbbW7pj5y8SPcCCakrPQQyw", "image_width": 1280}, "Small Buttonquail_372.jpeg": {"image_description": "Northern Hawk Owl (Surnia ulula) \u00c2\u00b7 iNaturalist.org", "image_filename": "Small Buttonquail_372.jpeg", "image_format": "jpg", "image_height": 1024, "image_host": "inaturalist.org", "image_link": "https://static.inaturalist.org/photos/663104/large.jpg?1391549134", "image_source": "https://www.inaturalist.org/taxa/20372-Surnia-ulula", "image_thumbnail_url": "https://encrypted-tbn0.gstatic.com/images?q=tbn:ANd9GcTL-rwhRD8hYQzH4Tdkq0VG0H6hUrS0HU1Ynloa-9i2uXY-gSDP4A", "image_width": 844}, "Yunnan Nuthatch_61.jpeg": {"image_description": "NORTHERN HAWK OWL CATCH MOUSE - YouTube", "image_filename": "Yunnan Nuthatch_61.jpeg", "image_format": "jpg", "image_height": 720, "image_host": "youtube.com", "image_link": "https://i.ytimg.com/vi/gKXd41aF8G4/maxresdefault.jpg", "image_source": "https://www.youtube.com/watch?v=gKXd41aF8G4", "image_thumbnail_url": "https://encrypted-tbn0.gstatic.com/images?q=tbn:ANd9GcTfxn8NP6-qQhZgOWGzlXpduIrjJ0h5NAEXgximTzDrg8r6Qg8TkA", "image_width": 1280}, "Yellowish-bellied Bush Warbler_399.jpeg": {"image_description": "Northern Hawk Owl - YouTube", "image_filename": "Yellowish-bellied Bush Warbler_399.jpeg", "image_format": "jpg", "image_height": 720, "image_host": "youtube.com", "image_link": "https://i.ytimg.com/vi/6VW6kKK3JZw/maxresdefault.jpg", "image_source": "https://www.youtube.com/watch?v=6VW6kKK3JZw", "image_thumbnail_url": "https://encrypted-tbn0.gstatic.com/images?q=tbn:ANd9GcT2ov_l52H1oF4Rp9n_ZTtKt13Pk1KIWua9sydwemQmfdI70FKJ", "image_width": 1280}, "White Swan_164.jpeg": {"image_description": "Northern Hawk Owl Stock Video Footage - 4K and HD Video Clips ...", "image_filename": "White Swan_164.jpeg", "image_format": "jpg", "image_height": 270, "image_host": "shutterstock.com", "image_link": "https://ak2.picdn.net/shutterstock/videos/1024556672/thumb/1.jpg?ip=x480", "image_source": "https://www.shutterstock.com/video/search/northern-hawk-owl", "image_thumbnail_url": "https://encrypted-tbn0.gstatic.com/images?q=tbn:ANd9GcQtwxvfCjDlOJqGVWKco1hLY0R5-T3xvx-HqTNeC1aduVTwJHox", "image_width": 480}, "White-cheeked Starling_329.jpeg": {"image_description": "Northern Hawk-Owl with prey - YouTube", "image_filename": "White-cheeked Starling_329.jpeg", "image_format": "jpg", "image_height": 720, "image_host": "youtube.com", "image_link": "https://i.ytimg.com/vi/D_-dKsECeDQ/maxresdefault.jpg", "image_source": "https://www.youtube.com/watch?v=D_-dKsECeDQ", "image_thumbnail_url": "https://encrypted-tbn0.gstatic.com/images?q=tbn:ANd9GcTmwAgJDvJ3segrr5lRIYIAXHHp2gS-_n2jbAu-AnBDSiPU5Teq2A", "image_width": 1280}}