{"Tiger Shrike_48.jpeg": {"image_description": "The Rufous Necked Hornbill (Aceros nipalensis)", "image_filename": "Tiger Shrike_48.jpeg", "image_format": "jpg", "image_height": 720, "image_host": "youtube.com", "image_link": "https://i.ytimg.com/vi/Q8CIZsPPSDc/maxresdefault.jpg", "image_source": "https://www.youtube.com/watch?v=Q8CIZsPPSDc", "image_thumbnail_url": "https://encrypted-tbn0.gstatic.com/images?q=tbn:ANd9GcS3ke8Xn2EgupW9jc_ymLv-V9Uu3Bf8BZw5THgh-790nWgGZuV7pg", "image_width": 1280}, "Yellow-necked koklass pheasa_31.jpeg": {"image_description": "Rufous necked hornbill", "image_filename": "Yellow-necked koklass pheasa_31.jpeg", "image_format": "jpg", "image_height": 720, "image_host": "youtube.com", "image_link": "https://i.ytimg.com/vi/GuuKfI3HFVs/maxresdefault.jpg", "image_source": "https://www.youtube.com/watch?v=GuuKfI3HFVs", "image_thumbnail_url": "https://encrypted-tbn0.gstatic.com/images?q=tbn:ANd9GcQTunzAxtKZ9Veww6VZpBiPaCVbGMibsfx14vOjUYJ4lwzk1OM", "image_width": 1280}, "Yellow-bellied Flowerpecker_188.jpeg": {"image_description": "Rufous Necked Hornbill", "image_filename": "Yellow-bellied Flowerpecker_188.jpeg", "image_format": "jpg", "image_height": 720, "image_host": "youtube.com", "image_link": "https://i.ytimg.com/vi/0feGNXcUAuE/maxresdefault.jpg", "image_source": "https://www.youtube.com/watch?v=0feGNXcUAuE", "image_thumbnail_url": "https://encrypted-tbn0.gstatic.com/images?q=tbn:ANd9GcSKeX2alzTLIAIj1J-YOxG8nawKuv0gtO1ygN4NFnZ9KwO9kmOzyQ", "image_width": 1280}, "Yellow-cheeked Tit_185.jpeg": {"image_description": "Rufous-necked Hornbill (Aceros nipalensis) \u00c2\u00b7 iNaturalist.org", "image_filename": "Yellow-cheeked Tit_185.jpeg", "image_format": "jpg", "image_height": 1800, "image_host": "inaturalist.org", "image_link": "https://static.inaturalist.org/photos/5411943/original.jpg?1478113924", "image_source": "https://www.inaturalist.org/taxa/5523-Aceros-nipalensis", "image_thumbnail_url": "https://encrypted-tbn0.gstatic.com/images?q=tbn:ANd9GcTvSGzqSTzVX6_AxNbnWXyafVtQPIyu75-PjQBMTS1JNBBBLr2-Qg", "image_width": 1200}, "White-winged Redstart_254.jpeg": {"image_description": "RUFOUS -NECKED HORNBILL || MALE || PREENING", "image_filename": "White-winged Redstart_254.jpeg", "image_format": "jpg", "image_height": 720, "image_host": "youtube.com", "image_link": "https://i.ytimg.com/vi/9TKV8wSX_qI/maxresdefault.jpg", "image_source": "https://www.youtube.com/watch?v=9TKV8wSX_qI", "image_thumbnail_url": "https://encrypted-tbn0.gstatic.com/images?q=tbn:ANd9GcQjpE_ZY0NYyXvXg8W7uAYpPuzYzbmmp2tlKyf_gb7InOvCRge88A", "image_width": 1280}, "White-bellied Yuhina_304.jpeg": {"image_description": "Rufous-Necked Hornbill", "image_filename": "White-bellied Yuhina_304.jpeg", "image_format": "jpg", "image_height": 720, "image_host": "youtube.com", "image_link": "https://i.ytimg.com/vi/RqmTG6vfLVc/maxresdefault.jpg", "image_source": "https://www.youtube.com/watch?v=RqmTG6vfLVc", "image_thumbnail_url": "https://encrypted-tbn0.gstatic.com/images?q=tbn:ANd9GcRWj33dD2vJjc4RiCK-3JXQzy0PRlmS2bM3RTGAHVj3Lx5KsSH4jQ", "image_width": 1280}, "White-browed Laughingthrush_227.jpeg": {"image_description": "Rufous Necked hornbill", "image_filename": "White-browed Laughingthrush_227.jpeg", "image_format": "jpg", "image_height": 720, "image_host": "youtube.com", "image_link": "https://i.ytimg.com/vi/RvbK6UpXD7Y/maxresdefault.jpg", "image_source": "https://www.youtube.com/watch?v=RvbK6UpXD7Y", "image_thumbnail_url": "https://encrypted-tbn0.gstatic.com/images?q=tbn:ANd9GcRLYuyScuFb7NtxIxGvLm_bXi_upiGA4Gl9bNA3etDTRinYy7dS", "image_width": 1280}, "White-whiskered Laughingthrush_165.jpeg": {"image_description": "Rufous Necked Hornbill | Latpanchar | Birding", "image_filename": "White-whiskered Laughingthrush_165.jpeg", "image_format": "jpg", "image_height": 720, "image_host": "youtube.com", "image_link": "https://i.ytimg.com/vi/3FxsWriRSmQ/maxresdefault.jpg", "image_source": "https://www.youtube.com/watch?v=3FxsWriRSmQ", "image_thumbnail_url": "https://encrypted-tbn0.gstatic.com/images?q=tbn:ANd9GcQuAnVoeHAIiKNHSmhCrF3tTS_6vfu8wpf0Ct8aXdxAgMYDq61Suw", "image_width": 1280}, "White-browed Fantail_248.jpeg": {"image_description": "Rare clip of courtship of Rufous-necked Hornbills", "image_filename": "White-browed Fantail_248.jpeg", "image_format": "jpg", "image_height": 360, "image_host": "youtube.com", "image_link": "https://i.ytimg.com/vi/pt0qvxq4PAY/hqdefault.jpg", "image_source": "https://www.youtube.com/watch?v=pt0qvxq4PAY", "image_thumbnail_url": "https://encrypted-tbn0.gstatic.com/images?q=tbn:ANd9GcTnGN56SWIkhN8eE-lDmr3uWSRVnFL9_DfPstBbwZlMNe5cT1qX", "image_width": 480}, "White-collared Yuhina_123.jpeg": {"image_description": "Latpanchar: The Place of Rufous Necked Hornbill ## 9", "image_filename": "White-collared Yuhina_123.jpeg", "image_format": "jpg", "image_height": 720, "image_host": "youtube.com", "image_link": "https://i.ytimg.com/vi/SDKeh7y27Tg/maxresdefault.jpg", "image_source": "https://www.youtube.com/watch?v=SDKeh7y27Tg", "image_thumbnail_url": "https://encrypted-tbn0.gstatic.com/images?q=tbn:ANd9GcSdLRCYW1bXkdin179jN6x-mHE_nUkdyq5oS99QLyHJbnqXlepG-w", "image_width": 1280}, "Corn Bunting_262.jpeg": {"image_description": "Close-up of Vulnerable Rufous-necked Hornbill (Female) - 1", "image_filename": "Corn Bunting_262.jpeg", "image_format": "jpg", "image_height": 360, "image_host": "youtube.com", "image_link": "https://i.ytimg.com/vi/bPiVR8nHl7k/hqdefault.jpg", "image_source": "https://www.youtube.com/watch?v=bPiVR8nHl7k", "image_thumbnail_url": "https://encrypted-tbn0.gstatic.com/images?q=tbn:ANd9GcTqi_60lE6NUqE8ICtmcTLXwsJn5fAVZRCQskPtqVkLIwxgYOnP", "image_width": 480}, "Stock Pigeon_40.jpeg": {"image_description": "Rufous Necked Hornbill(Orange head male,Black body female)", "image_filename": "Stock Pigeon_40.jpeg", "image_format": "jpg", "image_height": 720, "image_host": "youtube.com", "image_link": "https://i.ytimg.com/vi/om_6iJ6rt38/maxresdefault.jpg", "image_source": "https://www.youtube.com/watch?v=om_6iJ6rt38", "image_thumbnail_url": "https://encrypted-tbn0.gstatic.com/images?q=tbn:ANd9GcTUtneGZmycNjhGKJiEKI-HX-By9-pkTt2EOELlxsxStPBaMk_Ntg", "image_width": 1280}}