{"White-throated Fantail_274.jpeg": {"image_description": "Pallas's Grasshopper Warbler \u00e5\u00b0\u008f\u00e8\u009d\u0097\u00e8\u008e\u00ba / Rusty-rumped Warbler Apr2019 ...", "image_filename": "White-throated Fantail_274.jpeg", "image_format": "jpg", "image_height": 720, "image_host": "youtube.com", "image_link": "https://i.ytimg.com/vi/UEr8CrHtx_8/maxresdefault.jpg", "image_source": "https://www.youtube.com/watch?v=UEr8CrHtx_8", "image_thumbnail_url": "https://encrypted-tbn0.gstatic.com/images?q=tbn:ANd9GcRDVInH6oame_093HnJO_3uhjortq6rxeYH5oa2Sqc54wMLSR88TQ", "image_width": 1280}, "Chestnut-crowned Warbler_296.jpeg": {"image_description": "Wood Warblers Archives \u00c2\u00bb Page 2 of 3 \u00c2\u00bb Bird Watcher's Digest", "image_filename": "Chestnut-crowned Warbler_296.jpeg", "image_format": "jpg", "image_height": 404, "image_host": "birdwatchersdigest.com", "image_link": "https://www.birdwatchersdigest.com/bwdsite/wp-content/uploads/2016/11/BHENRY_CSWA_600.jpg", "image_source": "https://www.birdwatchersdigest.com/bwdsite/category/learn/identification/wood-warblers/page/2/", "image_thumbnail_url": "https://encrypted-tbn0.gstatic.com/images?q=tbn:ANd9GcRvPjimVz6if75wV2PeDO4p0lJUvv2RZD21EcLPqJazC4omdmnlsg", "image_width": 600}, "Variegated Laughingthrush_76.jpeg": {"image_description": "\u00e0\u00b8\u0099\u00e0\u00b8\u0081\u00e0\u00b8\u009e\u00e0\u00b8\u0087\u00e0\u00b8\u0095\u00e0\u00b8\u00b1\u00e0\u00b9\u008a\u00e0\u00b8\u0081\u00e0\u00b9\u0081\u00e0\u00b8\u0095\u00e0\u00b8\u0099\u00e0\u00b8\u0097\u00e0\u00b9\u0089\u00e0\u00b8\u00b2\u00e0\u00b8\u00a2\u00e0\u00b8\u0097\u00e0\u00b8\u00ad\u00e0\u00b8\u00a2\u00e0\u00b8\u00aa\u00e0\u00b8\u00b5\u00e0\u00b9\u0080\u00e0\u00b8\u0097\u00e0\u00b8\u00b2 / Rusty-rumped Warbler", "image_filename": "Variegated Laughingthrush_76.jpeg", "image_format": "jpg", "image_height": 720, "image_host": "youtube.com", "image_link": "https://i.ytimg.com/vi/aJSApvWvBh8/maxresdefault.jpg", "image_source": "https://www.youtube.com/watch?v=aJSApvWvBh8", "image_thumbnail_url": "https://encrypted-tbn0.gstatic.com/images?q=tbn:ANd9GcS38ylwbJL1vGAAuqqqbXlx4JjPVWUGtbeToS50Urv0vUfc7Y0PGQ", "image_width": 1280}, "Yellow-bellied Flowerpecker_99.jpeg": {"image_description": "Southern Scrub-robin (Drymodes brunneopygia)", "image_filename": "Yellow-bellied Flowerpecker_99.jpeg", "image_format": "jpg", "image_height": 720, "image_host": "youtube.com", "image_link": "https://i.ytimg.com/vi/1vLdKqFdiHc/maxresdefault.jpg", "image_source": "https://www.youtube.com/watch?v=1vLdKqFdiHc", "image_thumbnail_url": "https://encrypted-tbn0.gstatic.com/images?q=tbn:ANd9GcQVzNNae9eohCRjd3klCUhX8bzA9me3becLtUcKYwhZSv2Xx_5g", "image_width": 1280}, "Yellow Tit_261.jpeg": {"image_description": "Rusty Blackbird | American Bird Conservancy", "image_filename": "Yellow Tit_261.jpeg", "image_format": "jpg", "image_height": 360, "image_host": "abcbirds.org", "image_link": "https://i.ytimg.com/vi/Wy-RKBvGQTo/hqdefault.jpg", "image_source": "https://abcbirds.org/bird/rusty-blackbird/", "image_thumbnail_url": "https://encrypted-tbn0.gstatic.com/images?q=tbn:ANd9GcQd3hufBYCuwLmZo_PnTo5gwm58HNCY-jfUS2Qex16GPH62OX7v", "image_width": 480}, "Spotted Nutcracker_195.jpeg": {"image_description": "Blackpoll Warbler | American Bird Conservancy", "image_filename": "Spotted Nutcracker_195.jpeg", "image_format": "jpg", "image_height": 720, "image_host": "abcbirds.org", "image_link": "https://i.ytimg.com/vi/_hP_EkmiJCM/maxresdefault.jpg", "image_source": "https://abcbirds.org/bird/blackpoll-warbler/", "image_thumbnail_url": "https://encrypted-tbn0.gstatic.com/images?q=tbn:ANd9GcQjVr8fEAthttuTQVrpC4bxH34O67doNiMKBxEMWhdVtnjFy6LJkg", "image_width": 1280}, "White-spectacled Warbler_80.jpeg": {"image_description": "Cyprus Crossbill (Subspecies Loxia curvirostra guillemardi ...", "image_filename": "White-spectacled Warbler_80.jpeg", "image_format": "jpg", "image_height": 328, "image_host": "inaturalist.org", "image_link": "https://static.inaturalist.org/photos/31687501/medium.jpg?1550735863", "image_source": "https://www.inaturalist.org/taxa/525506-Loxia-curvirostra-guillemardi", "image_thumbnail_url": "https://encrypted-tbn0.gstatic.com/images?q=tbn:ANd9GcQuo7B5-aqy_g7DOT3dEZm7uk5Rxnbrll7Q5ebNk1WfH_glFrNN", "image_width": 500}, "Silver-eared Mesia_211.jpeg": {"image_description": "Chestnut vented and Layards calls", "image_filename": "Silver-eared Mesia_211.jpeg", "image_format": "jpg", "image_height": 720, "image_host": "youtube.com", "image_link": "https://i.ytimg.com/vi/D3KosFefkDY/maxresdefault.jpg", "image_source": "https://www.youtube.com/watch?v=D3KosFefkDY", "image_thumbnail_url": "https://encrypted-tbn0.gstatic.com/images?q=tbn:ANd9GcTqkXn8tpjNStHL0ROqfjoNl1ZOgJBuC5hk5fV4h2pFSTzERrNp7Q", "image_width": 1280}, "Rufous-tailed Babbler_408.jpeg": {"image_description": "Kenya", "image_filename": "Rufous-tailed Babbler_408.jpeg", "image_format": "jpg", "image_height": 375, "image_host": "nikborrow.com", "image_link": "http://nikborrow.com/Nik_Borrow/Kenya_Birds__Passerines_N-Z_files/Media/Red-tailed-Chat/thumb.jpg", "image_source": "http://nikborrow.com/Nik_Borrow/Kenya_Birds__Passerines_N-Z.html", "image_thumbnail_url": "https://encrypted-tbn0.gstatic.com/images?q=tbn:ANd9GcSPQ8fKybnAkFkIht8n7eLEqZcGhwDqVbIyEOrY7KE4nabxmvT-", "image_width": 500}}