{"Grey-hooded Warbler_387.jpeg": {"image_description": "Mountain Scops Owl Call - YouTube", "image_filename": "Grey-hooded Warbler_387.jpeg", "image_format": "jpg", "image_height": 360, "image_host": "youtube.com", "image_link": "https://i.ytimg.com/vi/3N8vnd_Ekec/hqdefault.jpg", "image_source": "https://www.youtube.com/watch?v=3N8vnd_Ekec", "image_thumbnail_url": "https://encrypted-tbn0.gstatic.com/images?q=tbn:ANd9GcTbLms8Ipqa2I686Xfhoa-Wqe9jCkHgymWZphyQjqApaPRqD-56hg", "image_width": 480}, "Grey-sided Laughingthrush_9.jpeg": {"image_description": "Brown-and-white whistling owl identified as new species | CTV News", "image_filename": "Grey-sided Laughingthrush_9.jpeg", "image_format": "jpg", "image_height": 513, "image_host": "ctvnews.ca", "image_link": "https://www.ctvnews.ca/polopoly_fs/1.1156572.1360856385!/httpImage/image.jpg_gen/derivatives/landscape_620/image.jpg", "image_source": "https://www.ctvnews.ca/sci-tech/brown-and-white-whistling-owl-identified-as-new-species-1.1156568", "image_thumbnail_url": "https://encrypted-tbn0.gstatic.com/images?q=tbn:ANd9GcTaCiTNc96wu-JgSAUxZLYdY0lZQ_xhs5w9jPsJajJnxoCgVFAb", "image_width": 620}, "White-browed Shortwing_244.jpeg": {"image_description": "Mountain scops owl, \u00e9\u00bb\u0083\u00e5\u0098\u00b4\u00e8\u00a7\u0092\u00e9\u00b4\u009e - YouTube", "image_filename": "White-browed Shortwing_244.jpeg", "image_format": "jpg", "image_height": 720, "image_host": "youtube.com", "image_link": "https://i.ytimg.com/vi/CcSfJElpEdI/maxresdefault.jpg", "image_source": "https://www.youtube.com/watch?v=CcSfJElpEdI", "image_thumbnail_url": "https://encrypted-tbn0.gstatic.com/images?q=tbn:ANd9GcTSnHCEBzNKmL3sWRZIL19h0l4nEmebP5jnNebjiqR5etGst_M2", "image_width": 1280}, "Common Raven_249.jpeg": {"image_description": "Mountain Scops-Owl (Otus spilocephalus) \u00c2\u00b7 iNaturalist.org", "image_filename": "Common Raven_249.jpeg", "image_format": "jpg", "image_height": 1200, "image_host": "inaturalist.org", "image_link": "https://static.inaturalist.org/photos/1725240/original.jpg?1429080156", "image_source": "https://www.inaturalist.org/taxa/20264-Otus-spilocephalus", "image_thumbnail_url": "https://encrypted-tbn0.gstatic.com/images?q=tbn:ANd9GcQrKG2NMMAMEkMksT-8F_N9zUCfWxReNejOK5G1cPWqWY-5eGrb", "image_width": 1800}, "Yellow-billed Grosbeak_3.jpeg": {"image_description": "7 owl calls from southern Africa - YouTube", "image_filename": "Yellow-billed Grosbeak_3.jpeg", "image_format": "jpg", "image_height": 720, "image_host": "youtube.com", "image_link": "https://i.ytimg.com/vi/xgxO0D7h2eI/maxresdefault.jpg", "image_source": "https://www.youtube.com/watch?v=xgxO0D7h2eI", "image_thumbnail_url": "https://encrypted-tbn0.gstatic.com/images?q=tbn:ANd9GcTjME21fTHHaQ9lm8FTokk0TizO0NZrHx5-ERRYlp5onMyNxNu-", "image_width": 1280}, "Tibetan Lark_39.jpeg": {"image_description": "When owls greet the camera | owls| Ceylon Frogmouth| Spotted Owlet ...", "image_filename": "Tibetan Lark_39.jpeg", "image_format": "jpg", "image_height": 867, "image_host": "english.mathrubhumi.com", "image_link": "https://english.mathrubhumi.com/polopoly_fs/1.1947477!/image/image.jpg_gen/derivatives/landscape_607/image.jpg", "image_source": "https://english.mathrubhumi.com/travel/features/when-owls-greet-the-camera-owls-in-kerala-birding-birdwatching-bird-wildlife-photography-1.1947473", "image_thumbnail_url": "https://encrypted-tbn0.gstatic.com/images?q=tbn:ANd9GcS2Df2671c7WGeGQ1fAFtQnQp8d517pyFhLK89T7oWnArOnIdkC", "image_width": 607}, "White-browed Scimitar Babbler_229.jpeg": {"image_description": "How to draw a spotted owl", "image_filename": "White-browed Scimitar Babbler_229.jpeg", "image_format": "jpg", "image_height": 720, "image_host": "marchtogether.com", "image_link": "https://i.ytimg.com/vi/cYe8zRuowA0/maxresdefault.jpg", "image_source": "http://marchtogether.com/victoria/how-to-draw-a-spotted-owl.php", "image_thumbnail_url": "https://encrypted-tbn0.gstatic.com/images?q=tbn:ANd9GcQp6caJZdLhA_jYf68bzxp2CXIsiEvWtoSY2BBXepXmBxNF5QqxlQ", "image_width": 1280}, "Thick-billed Green Pigeon_78.jpeg": {"image_description": "7 owl calls from southern Africa - YouTube", "image_filename": "Thick-billed Green Pigeon_78.jpeg", "image_format": "jpg", "image_height": 720, "image_host": "youtube.com", "image_link": "https://i.ytimg.com/vi/xgxO0D7h2eI/maxresdefault.jpg", "image_source": "https://www.youtube.com/watch?v=xgxO0D7h2eI", "image_thumbnail_url": "https://encrypted-tbn0.gstatic.com/images?q=tbn:ANd9GcTjME21fTHHaQ9lm8FTokk0TizO0NZrHx5-ERRYlp5onMyNxNu-", "image_width": 1280}, "Cinereous Vulture_176.jpeg": {"image_description": "Owls - alexander voda", "image_filename": "Cinereous Vulture_176.jpeg", "image_format": "jpg", "image_height": 512, "image_host": "alexandervoda.com", "image_link": "https://image.jimcdn.com/app/cms/image/transf/dimension=768x10000:format=jpg/path/s89f6e751e5ee7784/image/i0b0d352ee33b3089/version/1560756726/image.jpg", "image_source": "https://www.alexandervoda.com/portfolio/owls/", "image_thumbnail_url": "https://encrypted-tbn0.gstatic.com/images?q=tbn:ANd9GcSPrS9ub9yrVff1Q5ekl8LydJup9gZmDylYb_AaK_McNL5O4fbc", "image_width": 768}, "Pleske's Warbler_48.jpeg": {"image_description": "AVoCet : Strigidae", "image_filename": "Pleske's Warbler_48.jpeg", "image_format": "jpg", "image_height": 2592, "image_host": "avocet.integrativebiology.natsci.msu.edu", "image_link": "https://avocet.integrativebiology.natsci.msu.edu/photos_data/913/original.jpg", "image_source": "https://avocet.integrativebiology.natsci.msu.edu/families/267", "image_thumbnail_url": "https://encrypted-tbn0.gstatic.com/images?q=tbn:ANd9GcScAIChtm75jgIPkt_RS86DzN0Iz0b6VhSWp-zi03w9LouI6v8ZSg", "image_width": 3872}, "Common Snipe_264.jpeg": {"image_description": "Mountain Scops-Owl (Otus spilocephalus) \u00c2\u00b7 iNaturalist.org", "image_filename": "Common Snipe_264.jpeg", "image_format": "jpg", "image_height": 643, "image_host": "inaturalist.org", "image_link": "https://static.inaturalist.org/photos/4968374/large.jpg?1474533042", "image_source": "https://www.inaturalist.org/taxa/20264-Otus-spilocephalus", "image_thumbnail_url": "https://encrypted-tbn0.gstatic.com/images?q=tbn:ANd9GcSmQ_2U1hJswmaEto6t14BgHZDkkgN4fBzHRP7PAeRZLzvvcR1rjw", "image_width": 960}, "Northern Harrier_83.jpeg": {"image_description": "Spotted scops owl \u00e9\u00bb\u0083\u00e5\u0098\u00b4\u00e8\u00a7\u0092\u00e9\u00b4\u009e- YouTube", "image_filename": "Northern Harrier_83.jpeg", "image_format": "jpg", "image_height": 360, "image_host": "youtube.com", "image_link": "https://i.ytimg.com/vi/52RPUYDB6eE/hqdefault.jpg?w=160&h=120&sigh=ZtDrsPqjhvVI_5PEc__euPP238Q", "image_source": "https://www.youtube.com/watch?v=52RPUYDB6eE", "image_thumbnail_url": "https://encrypted-tbn0.gstatic.com/images?q=tbn:ANd9GcRNAWD41OrVAUkNSzeXtDUnq7kRFlMFUf333FXPVu0mLh7oFDPs", "image_width": 480}, "Northern Wheatear_19.jpeg": {"image_description": "Can you spot the owl in this photo?", "image_filename": "Northern Wheatear_19.jpeg", "image_format": "jpg", "image_height": 360, "image_host": "telegraph.co.uk", "image_link": "https://i.ytimg.com/vi/_UVaIBq2eAQ/hqdefault.jpg", "image_source": "https://www.telegraph.co.uk/news/2016/09/08/can-you-spot-the-owl-in-this-photo/", "image_thumbnail_url": "https://encrypted-tbn0.gstatic.com/images?q=tbn:ANd9GcToAhooE3o3roFexrMrz5uAEdgGhaz6W9CJ2JerXFJVgmrSDBuO", "image_width": 480}, "Tibetan Snowfinch_213.jpeg": {"image_description": "When owls greet the camera | owls| Ceylon Frogmouth| Spotted Owlet ...", "image_filename": "Tibetan Snowfinch_213.jpeg", "image_format": "jpg", "image_height": 404, "image_host": "english.mathrubhumi.com", "image_link": "https://english.mathrubhumi.com/polopoly_fs/1.1947484!/image/image.jpg_gen/derivatives/landscape_607/image.jpg", "image_source": "https://english.mathrubhumi.com/travel/features/when-owls-greet-the-camera-owls-in-kerala-birding-birdwatching-bird-wildlife-photography-1.1947473", "image_thumbnail_url": "https://encrypted-tbn0.gstatic.com/images?q=tbn:ANd9GcS2I4fxurkmTCag4yA7OOKtzmqmvlhVTig-4t8p0mgFxXBozWMK", "image_width": 607}, "Robin Accentor_190.jpeg": {"image_description": "Mountain scops owl - Alchetron, The Free Social Encyclopedia", "image_filename": "Robin Accentor_190.jpeg", "image_format": "jpg", "image_height": 360, "image_host": "alchetron.com", "image_link": "https://i.ytimg.com/vi/eAzIk2ml-sI/hqdefault.jpg", "image_source": "https://alchetron.com/Mountain-scops-owl", "image_thumbnail_url": "https://encrypted-tbn0.gstatic.com/images?q=tbn:ANd9GcR0f3gtufLp8xf2jgbRHHjm3gWpNiH7CeIlzXjKyHak6K1buSyl5w", "image_width": 480}, "Yellow-breasted Greenfinch_396.jpeg": {"image_description": "Endemic Bird Species of Cyprus - CYPRUS BIRD WATCHING TOURS - BIRD ...", "image_filename": "Yellow-breasted Greenfinch_396.jpeg", "image_format": "jpg", "image_height": 720, "image_host": "birdingtourscyprus-bitw.com", "image_link": "https://i.ytimg.com/vi/aTZCwhxWhUA/maxresdefault.jpg", "image_source": "http://www.birdingtourscyprus-bitw.com/endemics.html", "image_thumbnail_url": "https://encrypted-tbn0.gstatic.com/images?q=tbn:ANd9GcQXCqcDeXKY0CWBhyvWO6rYReQXcFeRCxCraL1UzMruNkxl1vGKqQ", "image_width": 1280}, "Fulvous-breasted Woodpecker_203.jpeg": {"image_description": "Scops Owls (Genus Otus) \u00c2\u00b7 iNaturalist.org", "image_filename": "Fulvous-breasted Woodpecker_203.jpeg", "image_format": "jpg", "image_height": 500, "image_host": "inaturalist.org", "image_link": "https://static.inaturalist.org/photos/164284/medium.jpg?1545375331", "image_source": "https://www.inaturalist.org/taxa/20190-Otus", "image_thumbnail_url": "https://encrypted-tbn0.gstatic.com/images?q=tbn:ANd9GcTNIFmth8klns03xYwQK5KIBNXtWn-4ug-EOnz1PROYdhgjns5kBg", "image_width": 318}, "Slender-billed Scimitar-B_334.jpeg": {"image_description": "When owls greet the camera | owls| Ceylon Frogmouth| Spotted Owlet ...", "image_filename": "Slender-billed Scimitar-B_334.jpeg", "image_format": "jpg", "image_height": 875, "image_host": "english.mathrubhumi.com", "image_link": "https://english.mathrubhumi.com/polopoly_fs/1.1947482!/image/image.jpg_gen/derivatives/landscape_607/image.jpg", "image_source": "https://english.mathrubhumi.com/travel/features/when-owls-greet-the-camera-owls-in-kerala-birding-birdwatching-bird-wildlife-photography-1.1947473", "image_thumbnail_url": "https://encrypted-tbn0.gstatic.com/images?q=tbn:ANd9GcQcvoO5KbxpdmzaajwUXueXJwW8c-usr-xEKaE1-4EyOvoUkMxI", "image_width": 607}, "Small Niltava_222.jpeg": {"image_description": "Spotted Wood Owl in Malaysia Rainforest - YouTube", "image_filename": "Small Niltava_222.jpeg", "image_format": "jpg", "image_height": 720, "image_host": "youtube.com", "image_link": "https://i.ytimg.com/vi/wJGKTtzzPz0/maxresdefault.jpg", "image_source": "https://www.youtube.com/watch?v=wJGKTtzzPz0", "image_thumbnail_url": "https://encrypted-tbn0.gstatic.com/images?q=tbn:ANd9GcTCftXJ53HMI9EQVEsq8XUwZtJaJmtC4VzJrOS39YYiNgTdqAnVCQ", "image_width": 1280}, "Chestnut-cheeked Starling_241.jpeg": {"image_description": "AVoCet : Strigidae", "image_filename": "Chestnut-cheeked Starling_241.jpeg", "image_format": "jpg", "image_height": 1944, "image_host": "avocet.integrativebiology.natsci.msu.edu", "image_link": "https://avocet.integrativebiology.natsci.msu.edu/photos_data/487/original.jpg", "image_source": "https://avocet.integrativebiology.natsci.msu.edu/families/267", "image_thumbnail_url": "https://encrypted-tbn0.gstatic.com/images?q=tbn:ANd9GcQDoaUAYDriunboZHwkUWAMFA4I5ElvC6KVUf3qyXDtUkU9JGcuHA", "image_width": 1296}, "Java Sparrow_225.jpeg": {"image_description": "Southern White-faced Scops-Owl", "image_filename": "Java Sparrow_225.jpeg", "image_format": "jpg", "image_height": 700, "image_host": "stellenboschbirds.com", "image_link": "http://www.stellenboschbirds.com/basImages/1.jpg", "image_source": "http://www.stellenboschbirds.com/owlet.html", "image_thumbnail_url": "https://encrypted-tbn0.gstatic.com/images?q=tbn:ANd9GcS6JMB56sZEqw5SwZHLgDkYov-qy-op2UvaVyMZolpPC2OWLxQI", "image_width": 482}, "White-backed Woodpecker_358.jpeg": {"image_description": "Serendib scops owl (Otus thilohoffmanni) - YouTube", "image_filename": "White-backed Woodpecker_358.jpeg", "image_format": "jpg", "image_height": 720, "image_host": "youtube.com", "image_link": "https://i.ytimg.com/vi/hxXVV1BEeks/maxresdefault.jpg", "image_source": "https://www.youtube.com/watch?v=hxXVV1BEeks", "image_thumbnail_url": "https://encrypted-tbn0.gstatic.com/images?q=tbn:ANd9GcScVy9jNuwkU0KQFzVkWyP2TKMUc9w-bbpHhmKCcKCBDmA2buNE", "image_width": 1280}}